{
    "$schema": "https://vega.github.io/schema/vega-lite/v6.json",
    "title": "CO Emissions Load By Source (2022)",
    "width": 300,
    "height": 300,
    "background": null,
    "layer": [
        {
            "data": {
                "values": [
                    {
                        "source": "Motor Vehicles",
                        "tonnage": "1997005"
                    },
                    {
                        "source": "Industries",
                        "tonnage": "8547"
                    },
                    {
                        "source": "Power stations",
                        "tonnage": "61153"
                    },
                    {
                        "source": "Others",
                        "tonnage": "4204"
                    }
                ]
            },
            "mark": {
                "type": "arc",
                "innerRadius": 75
            },
            "encoding": {
                "theta": {
                    "field": "tonnage",
                    "type": "quantitative"
                },
                "color": {
                    "field": "source",
                    "type": "nominal",
                    "title": "Pollution Source"
                },
                "tooltip": [
                    {
                        "field": "tonnage",
                        "title": "Tonnage",
                        "type": "quantitative"
                    },
                    {
                        "field": "source",
                        "title": "Source",
                        "type": "nominal"
                    }
                ]
            }
        },
        {
            "data": {
                "values": [
                    {}
                ]
            },
            "mark": {
                "type": "text",
                "align": "center",
                "baseline": "middle",
                "fontSize": 12,
                "fontWeight": "bold",
                "dy": -28
            },
            "encoding": {
                "text": {
                    "value": "Total CO Emissions:"
                }
            }
        },
        {
            "data": {
                "values": [
                    {}
                ]
            },
            "mark": {
                "type": "text",
                "align": "center",
                "baseline": "middle",
                "fontSize": 24,
                "fontWeight": "bold",
                "dy": 10
            },
            "encoding": {
                "text": {
                    "value": "2070909 "
                }
            }
        },
        {
            "data": {
                "values": [
                    {}
                ]
            },
            "mark": {
                "type": "text",
                "align": "center",
                "baseline": "middle",
                "fontSize": 14,
                "fontWeight": "bold",
                "dy": 32
            },
            "encoding": {
                "text": {
                    "value": "metric tonnes"
                }
            }
        }
    ],
    "config": {
        "style": {
            "cell": {
                "stroke": "transparent"
            }
        }
    }
}